{
  "common": {
    "root_dir": "/usr/xtmp/superresoluter/superresolution",
    "hr_dir": "imgs/source_image/RealSR/TrainGT",
    "lr_dir": "imgs/source_image/RealSR/TrainLR",
    "sr_dir": "imgs/stage_one_image/{}/RealSR",
    "tto_dir": "imgs/stage_two_image/{}-{}/RealSR/",
    "tto_log": "imgs/stage_two_image/{}-{}/RealSR/tto.log",
    "train_log": "logs/{}.log",
    "ckpt_dir": "checkpoints/{}.ckpt"
  },
  "train": {
    "device_ids": 0,
    "batch_size": 300,
    "num_epoch": 300,
    "window": [40, 40],
    "learning_rate": 1e-4,
    "decay_rate": 0.1,
    "decay_step": 80,
    "num_per": 600,
    "loss": ["MSE"],
    "metric": ["PSNR"],
    "optimizer": null,
    "l2_beta": 1e-3,
    "num_worker": 6,
    "map_location": null,
    "save_every": 5,
    "print_every": 5
  },
  "tto": {
    "method": "bicubic+reg+vgg_discriminator",
    "learning_rate": 1e-2,
    "beta": 1e-2,
    "beta_1": 1e-3,
    "num_epoch": 500,
    "save": true,
    "rgb_shuffle": false,
    "print_every": 100,
    "disk_ckpt": "checkpoints/155000_D.pth",
    "device_name": "cuda:0"
  }
}
